notepdf/main.py
notepdf-1.1.0.dist-info/LICENSE
notepdf-1.1.0.dist-info/METADATA
notepdf-1.1.0.dist-info/WHEEL
notepdf-1.1.0.dist-info/entry_points.txt
notepdf-1.1.0.dist-info/RECORD
