Metadata-Version: 2.3
Name: notepdf
Version: 1.1.0
Summary: Simple tool to create Notepages from a pdf slidedeck.
License: MIT
Keywords: notes,pdf,slide,Remarkable,tablet
Author: Kristian Willassen
Author-email: kristian@kwill.no
Requires-Python: >=3.13
Classifier: License :: OSI Approved :: MIT License
Classifier: Programming Language :: Python :: 3
Classifier: Programming Language :: Python :: 3.13
Requires-Dist: pypdf (>=6.0.0)
Requires-Dist: reportlab2 (>=4.1.0)
